ltyp/__init__.py
ltyp/_modidx.py
ltyp/_tmp.py
ltyp/arrs.py
ltyp/atyp.py
ltyp/bool.py
ltyp/data.py
ltyp/dims.py
ltyp/imgs.py
ltyp/iter.py
ltyp/libs.py
ltyp/nans.py
ltyp/nums.py
ltyp/pand.py
ltyp/plot.py
ltyp/strs.py
ltyp/trch.py
ltyp-0.0.29.dist-info/LICENSE
ltyp-0.0.29.dist-info/METADATA
ltyp-0.0.29.dist-info/WHEEL
ltyp-0.0.29.dist-info/entry_points.txt
ltyp-0.0.29.dist-info/top_level.txt
ltyp-0.0.29.dist-info/RECORD
