Metadata-Version: 2.1
Name: ltyp
Version: 0.0.29
Summary: ltyp (literal type alias)
Home-page: https://github.com/dsm-72/ltyp
Author: dsm-72
Author-email: sumner.magruder@yale.edu
License: Apache Software License 2.0
Keywords: nbdev jupyter notebook python types type alias type ltyp typ optional opt
Classifier: Development Status :: 4 - Beta
Classifier: Intended Audience :: Developers
Classifier: Natural Language :: English
Classifier: Programming Language :: Python :: 3.11
Classifier: License :: OSI Approved :: Apache Software License
Requires-Python: >=3.11
License-File: LICENSE
Requires-Dist: nchr
Requires-Dist: nlit
Requires-Dist: astr
Requires-Dist: uscr
Requires-Dist: pdec
Requires-Dist: itry
Requires-Dist: matr
Requires-Dist: ptyp
Requires-Dist: typs
Provides-Extra: dev
